adaptera/__init__.py
adaptera/chains/__init__.py
adaptera/chains/agent.py
adaptera/memory/__init__.py
adaptera/memory/core.py
adaptera/model/__init__.py
adaptera/model/core.py
adaptera/tools/__init__.py
adaptera/tools/registry.py
adaptera-0.1.1.dist-info/licenses/LICENSE
adaptera-0.1.1.dist-info/METADATA
adaptera-0.1.1.dist-info/WHEEL
adaptera-0.1.1.dist-info/top_level.txt
adaptera-0.1.1.dist-info/RECORD
