Metadata-Version: 2.4
Name: adaptera
Version: 0.1.1
Summary: A local-first LLM orchestration library
Author: Sylo
License-Expression: MIT
Keywords: llm,orchestration,local-first,ai,machine-learning
Classifier: Development Status :: 3 - Alpha
Classifier: Intended Audience :: Developers
Classifier: Programming Language :: Python :: 3
Classifier: Programming Language :: Python :: 3.12
Classifier: Topic :: Scientific/Engineering :: Artificial Intelligence
Requires-Python: >=3.12
License-File: LICENSE
Requires-Dist: torch>=2.0.0
Requires-Dist: transformers>=4.40.0
Requires-Dist: peft>=0.10.0
Requires-Dist: accelerate>=0.29.0
Requires-Dist: bitsandbytes>=0.43.0
Requires-Dist: numpy>=1.24.0
Requires-Dist: faiss-cpu>=1.8.0
Provides-Extra: dev
Requires-Dist: pytest; extra == "dev"
Requires-Dist: build; extra == "dev"
Requires-Dist: twine; extra == "dev"
Dynamic: license-file
